{
  "db_name": "SQLite",
  "query": "\n        SELECT date(o.effective_start) AS \"bucket!: String\",\n               sd.source AS \"source!: String\",\n               sd.document_date AS \"document_date?: String\"\n        FROM observations o\n        JOIN source_documents sd ON o.source_document_id = sd.id\n        WHERE o.coding_system = ?\n          AND o.coding_code = ?\n          AND o.effective_start >= ?\n          AND o.effective_start < ?\n          AND o.effective_end IS NOT NULL\n          AND o.value_quantity >= ?\n          AND o.value_quantity <= ?\n        GROUP BY date(o.effective_start), sd.source, sd.document_date\n        ",
  "describe": {
    "columns": [
      {
        "name": "bucket!: String",
        "ordinal": 0,
        "type_info": "Null"
      },
      {
        "name": "source!: String",
        "ordinal": 1,
        "type_info": "Text"
      },
      {
        "name": "document_date?: String",
        "ordinal": 2,
        "type_info": "Text"
      }
    ],
    "parameters": {
      "Right": 6
    },
    "nullable": [
      null,
      false,
      true
    ]
  },
  "hash": "0275f62c55ffbf0b45d8b9df9b27607d8f0795f52cdc862b306fc9706dcd19f5"
}
